[
  {
    "headingType": "demographicGroupTerm",
    "listDate": "2022-06-03",
    "listSource": "https://classweb.org/approved-subjects/2206x.html",
    "LCLinkedDataURI": "http://id.loc.gov/authorities/demographicterms/dg2022060106",
    "LCCNPermalink": null,
    "statusApprovedBeforeMeeting": false,
    "statusSubmittedByCoopLib": true,
    "statusNewHeading": true,
    "statusChangedHeading": false,
    "statusCancelledHeading": false,
    "statusUpdatedField": false,
    "statusAddedField": false,
    "statusDeletedField": false,
    "statusUpdatedGeog": false,
    "statusAddedGeog": false,
    "statusDeletedGeog": false,
    "statusChangedGeog": false,
    "lines": [
      "150 Ainu (Asian people)",
      "072 eth",
      "450 UF Aino (Asian people)",
      "450 UF Aynu (Asian people)",
      "450 UF Eino (Asian people)",
      "450 UF Ezo (Asian people)",
      "450 UF Hokkaido Ainu (Asian people)",
      "450 UF Kurile Ainu (Asian people)",
      "450 UF Sakhalin Ainu (Asian people)"
    ]
  },
  {
    "headingType": "demographicGroupTerm",
    "listDate": "2022-06-03",
    "listSource": "https://classweb.org/approved-subjects/2206x.html",
    "LCLinkedDataURI": "http://id.loc.gov/authorities/demographicterms/dg2022060127",
    "LCCNPermalink": null,
    "statusApprovedBeforeMeeting": false,
    "statusSubmittedByCoopLib": true,
    "statusNewHeading": true,
    "statusChangedHeading": false,
    "statusCancelledHeading": false,
    "statusUpdatedField": false,
    "statusAddedField": false,
    "statusDeletedField": false,
    "statusUpdatedGeog": false,
    "statusAddedGeog": false,
    "statusDeletedGeog": false,
    "statusChangedGeog": false,
    "lines": [
      "150 Alawites",
      "072 rel",
      "450 UF Alawi Muslims",
      "450 UF Alawis",
      "450 UF ʿAlawīyah",
      "450 UF ʿAlawiyya",
      "450 UF Ansaris",
      "450 UF Ansarīyah",
      "450 UF Namīrīyah",
      "450 UF Nusayris",
      "450 UF Nuṣayrīyah",
      "550 BT Shiites"
    ]
  },
  {
    "headingType": "demographicGroupTerm",
    "listDate": "2022-06-03",
    "listSource": "https://classweb.org/approved-subjects/2206x.html",
    "LCLinkedDataURI": "http://id.loc.gov/authorities/demographicterms/dg2022060128",
    "LCCNPermalink": null,
    "statusApprovedBeforeMeeting": false,
    "statusSubmittedByCoopLib": true,
    "statusNewHeading": true,
    "statusChangedHeading": false,
    "statusCancelledHeading": false,
    "statusUpdatedField": false,
    "statusAddedField": false,
    "statusDeletedField": false,
    "statusUpdatedGeog": false,
    "statusAddedGeog": false,
    "statusDeletedGeog": false,
    "statusChangedGeog": false,
    "lines": [
      "150 Bengali, Students of",
      "072 soc",
      "450 UF Bengali learners",
      "450 UF Bengali students",
      "450 UF Bangla, Students of",
      "450 UF Bangla learners",
      "450 UF Bangla students",
      "450 UF Learners, Bengali",
      "450 UF Learners, Bangla",
      "450 UF Students, Bengali",
      "450 UF Students of Bengali",
      "450 UF Students, Bangla",
      "450 UF Students of Bangla",
      "680 Students of Bengali language and/or Bengali literature."
    ]
  },
  {
    "headingType": "demographicGroupTerm",
    "listDate": "2022-06-03",
    "listSource": "https://classweb.org/approved-subjects/2206x.html",
    "LCLinkedDataURI": "http://id.loc.gov/authorities/demographicterms/dg2017060225",
    "LCCNPermalink": null,
    "statusApprovedBeforeMeeting": false,
    "statusSubmittedByCoopLib": true,
    "statusNewHeading": false,
    "statusChangedHeading": false,
    "statusCancelledHeading": false,
    "statusUpdatedField": true,
    "statusAddedField": true,
    "statusDeletedField": false,
    "statusUpdatedGeog": false,
    "statusAddedGeog": false,
    "statusDeletedGeog": false,
    "statusChangedGeog": false,
    "lines": [
      "150 Biology teachers",
      "680 Teachers of biology at any level. For teachers of students at a particular educational level, use also an occupational term for the level, e.g. High school teachers. ADD FIELD"
    ]
  },
  {
    "headingType": "demographicGroupTerm",
    "listDate": "2022-06-03",
    "listSource": "https://classweb.org/approved-subjects/2206x.html",
    "LCLinkedDataURI": "http://id.loc.gov/authorities/demographicterms/dg2022060134",
    "LCCNPermalink": null,
    "statusApprovedBeforeMeeting": false,
    "statusSubmittedByCoopLib": true,
    "statusNewHeading": true,
    "statusChangedHeading": false,
    "statusCancelledHeading": false,
    "statusUpdatedField": false,
    "statusAddedField": false,
    "statusDeletedField": false,
    "statusUpdatedGeog": false,
    "statusAddedGeog": false,
    "statusDeletedGeog": false,
    "statusChangedGeog": false,
    "lines": [
      "150 Boiseans",
      "072 nat",
      "450 UF Boise, Idaho, residents",
      "450 UF Boiseians",
      "450 UF Boiseites",
      "450 UF Boisians",
      "550 BT Idahoans"
    ]
  },
  {
    "headingType": "demographicGroupTerm",
    "listDate": "2022-06-03",
    "listSource": "https://classweb.org/approved-subjects/2206x.html",
    "LCLinkedDataURI": "http://id.loc.gov/authorities/demographicterms/dg2022060116",
    "LCCNPermalink": null,
    "statusApprovedBeforeMeeting": false,
    "statusSubmittedByCoopLib": true,
    "statusNewHeading": true,
    "statusChangedHeading": false,
    "statusCancelledHeading": false,
    "statusUpdatedField": false,
    "statusAddedField": false,
    "statusDeletedField": false,
    "statusUpdatedGeog": false,
    "statusAddedGeog": false,
    "statusDeletedGeog": false,
    "statusChangedGeog": false,
    "lines": [
      "150 Bulgarian, Students of",
      "072 soc",
      "450 UF Bulgarian learners",
      "450 UF Bulgarian students",
      "450 UF Learners, Bulgarian",
      "450 UF Students, Bulgarian",
      "450 UF Students of Bulgarian",
      "680 Students of Bulgarian language and/or Bulgarian literature."
    ]
  },
  {
    "headingType": "demographicGroupTerm",
    "listDate": "2022-06-03",
    "listSource": "https://classweb.org/approved-subjects/2206x.html",
    "LCLinkedDataURI": "http://id.loc.gov/authorities/demographicterms/dg2022060100",
    "LCCNPermalink": null,
    "statusApprovedBeforeMeeting": false,
    "statusSubmittedByCoopLib": true,
    "statusNewHeading": true,
    "statusChangedHeading": false,
    "statusCancelledHeading": false,
    "statusUpdatedField": false,
    "statusAddedField": false,
    "statusDeletedField": false,
    "statusUpdatedGeog": false,
    "statusAddedGeog": false,
    "statusDeletedGeog": false,
    "statusChangedGeog": false,
    "lines": [
      "150 Chagatai, Students of",
      "072 soc",
      "450 UF Chagatai learners",
      "450 UF Chagatai students",
      "450 UF Chaghatay, Students of",
      "450 UF Chaghatay learners",
      "450 UF Chaghatay students",
      "450 UF Learners, Chagatai",
      "450 UF Learners, Chaghatay",
      "450 UF Students, Chagatai",
      "450 UF Students, Chaghatay",
      "450 UF Students of Chagatai",
      "450 UF Students of Chaghatay",
      "680 Students of Chagatai language and/or Chagatai literature."
    ]
  },
  {
    "headingType": "demographicGroupTerm",
    "listDate": "2022-06-03",
    "listSource": "https://classweb.org/approved-subjects/2206x.html",
    "LCLinkedDataURI": "http://id.loc.gov/authorities/demographicterms/dg2022060103",
    "LCCNPermalink": null,
    "statusApprovedBeforeMeeting": false,
    "statusSubmittedByCoopLib": true,
    "statusNewHeading": true,
    "statusChangedHeading": false,
    "statusCancelledHeading": false,
    "statusUpdatedField": false,
    "statusAddedField": false,
    "statusDeletedField": false,
    "statusUpdatedGeog": false,
    "statusAddedGeog": false,
    "statusDeletedGeog": false,
    "statusChangedGeog": false,
    "lines": [
      "150 Chemometricians",
      "072 occ",
      "550 BT Chemists"
    ]
  },
  {
    "headingType": "demographicGroupTerm",
    "listDate": "2022-06-03",
    "listSource": "https://classweb.org/approved-subjects/2206x.html",
    "LCLinkedDataURI": "http://id.loc.gov/authorities/demographicterms/dg2022060135",
    "LCCNPermalink": null,
    "statusApprovedBeforeMeeting": false,
    "statusSubmittedByCoopLib": true,
    "statusNewHeading": true,
    "statusChangedHeading": false,
    "statusCancelledHeading": false,
    "statusUpdatedField": false,
    "statusAddedField": false,
    "statusDeletedField": false,
    "statusUpdatedGeog": false,
    "statusAddedGeog": false,
    "statusDeletedGeog": false,
    "statusChangedGeog": false,
    "lines": [
      "150 Clevelanders",
      "072 nat",
      "450 UF Cleveland, Ohio, residents",
      "550 BT Ohioans"
    ]
  },
  {
    "headingType": "demographicGroupTerm",
    "listDate": "2022-06-03",
    "listSource": "https://classweb.org/approved-subjects/2206x.html",
    "LCLinkedDataURI": "http://id.loc.gov/authorities/demographicterms/dg2015060424",
    "LCCNPermalink": null,
    "statusApprovedBeforeMeeting": false,
    "statusSubmittedByCoopLib": true,
    "statusNewHeading": false,
    "statusChangedHeading": false,
    "statusCancelledHeading": false,
    "statusUpdatedField": true,
    "statusAddedField": true,
    "statusDeletedField": true,
    "statusUpdatedGeog": false,
    "statusAddedGeog": false,
    "statusDeletedGeog": false,
    "statusChangedGeog": false,
    "lines": [
      "150 Czech speakers",
      "450 UF Cestina speakers DELETE FIELD",
      "450 UF Čeština speakers ADD FIELD",
      "450 UF Český jazyk speakers ADD FIELD",
      "450 UF Speakers of Czech ADD FIELD"
    ]
  },
  {
    "headingType": "demographicGroupTerm",
    "listDate": "2022-06-03",
    "listSource": "https://classweb.org/approved-subjects/2206x.html",
    "LCLinkedDataURI": "http://id.loc.gov/authorities/demographicterms/dg2022060118",
    "LCCNPermalink": null,
    "statusApprovedBeforeMeeting": false,
    "statusSubmittedByCoopLib": true,
    "statusNewHeading": true,
    "statusChangedHeading": false,
    "statusCancelledHeading": false,
    "statusUpdatedField": false,
    "statusAddedField": false,
    "statusDeletedField": false,
    "statusUpdatedGeog": false,
    "statusAddedGeog": false,
    "statusDeletedGeog": false,
    "statusChangedGeog": false,
    "lines": [
      "150 Czech, Students of",
      "072 soc",
      "450 UF Czech learners",
      "450 UF Czech students",
      "450 UF Learners, Czech",
      "450 UF Students, Czech",
      "450 UF Students of Czech",
      "680 Students of Czech language and/or Czech literature."
    ]
  },
  {
    "headingType": "demographicGroupTerm",
    "listDate": "2022-06-03",
    "listSource": "https://classweb.org/approved-subjects/2206x.html",
    "LCLinkedDataURI": "http://id.loc.gov/authorities/demographicterms/dg2022060121",
    "LCCNPermalink": null,
    "statusApprovedBeforeMeeting": false,
    "statusSubmittedByCoopLib": true,
    "statusNewHeading": true,
    "statusChangedHeading": false,
    "statusCancelledHeading": false,
    "statusUpdatedField": false,
    "statusAddedField": false,
    "statusDeletedField": false,
    "statusUpdatedGeog": false,
    "statusAddedGeog": false,
    "statusDeletedGeog": false,
    "statusChangedGeog": false,
    "lines": [
      "150 Dallasites",
      "072 nat",
      "450 UF Dallas, Texas, residents",
      "550 BT Texans"
    ]
  },
  {
    "headingType": "demographicGroupTerm",
    "listDate": "2022-06-03",
    "listSource": "https://classweb.org/approved-subjects/2206x.html",
    "LCLinkedDataURI": "http://id.loc.gov/authorities/demographicterms/dg2022060107",
    "LCCNPermalink": null,
    "statusApprovedBeforeMeeting": false,
    "statusSubmittedByCoopLib": true,
    "statusNewHeading": true,
    "statusChangedHeading": false,
    "statusCancelledHeading": false,
    "statusUpdatedField": false,
    "statusAddedField": false,
    "statusDeletedField": false,
    "statusUpdatedGeog": false,
    "statusAddedGeog": false,
    "statusDeletedGeog": false,
    "statusChangedGeog": false,
    "lines": [
      "150 Danish, Students of",
      "072 soc",
      "450 UF Danish learners",
      "450 UF Danish students",
      "450 UF Learners, Danish",
      "450 UF Students, Danish",
      "450 UF Students of Danish",
      "680 Students of Danish language and/or Danish literature."
    ]
  },
  {
    "headingType": "demographicGroupTerm",
    "listDate": "2022-06-03",
    "listSource": "https://classweb.org/approved-subjects/2206x.html",
    "LCLinkedDataURI": "http://id.loc.gov/authorities/demographicterms/dg2022060130",
    "LCCNPermalink": null,
    "statusApprovedBeforeMeeting": false,
    "statusSubmittedByCoopLib": true,
    "statusNewHeading": true,
    "statusChangedHeading": false,
    "statusCancelledHeading": false,
    "statusUpdatedField": false,
    "statusAddedField": false,
    "statusDeletedField": false,
    "statusUpdatedGeog": false,
    "statusAddedGeog": false,
    "statusDeletedGeog": false,
    "statusChangedGeog": false,
    "lines": [
      "150 Dari speakers",
      "072 lng",
      "450 UF Afghan Persian speakers",
      "450 UF Dari Persian speakers",
      "450 UF Eastern Farsi speakers",
      "450 UF Eastern Persian speakers",
      "450 UF Farsi, Eastern, speakers",
      "450 UF Persian, Afghan, speakers",
      "450 UF Persian, Dari, speakers",
      "450 UF Persian, Eastern, speakers"
    ]
  },
  {
    "headingType": "demographicGroupTerm",
    "listDate": "2022-06-03",
    "listSource": "https://classweb.org/approved-subjects/2206x.html",
    "LCLinkedDataURI": "http://id.loc.gov/authorities/demographicterms/dg2022060108",
    "LCCNPermalink": null,
    "statusApprovedBeforeMeeting": false,
    "statusSubmittedByCoopLib": true,
    "statusNewHeading": true,
    "statusChangedHeading": false,
    "statusCancelledHeading": false,
    "statusUpdatedField": false,
    "statusAddedField": false,
    "statusDeletedField": false,
    "statusUpdatedGeog": false,
    "statusAddedGeog": false,
    "statusDeletedGeog": false,
    "statusChangedGeog": false,
    "lines": [
      "150 Edmontonians",
      "072 nat",
      "450 UF Edmontoniens",
      "450 UF Oiltowners",
      "550 BT Albertans"
    ]
  },
  {
    "headingType": "demographicGroupTerm",
    "listDate": "2022-06-03",
    "listSource": "https://classweb.org/approved-subjects/2206x.html",
    "LCLinkedDataURI": "http://id.loc.gov/authorities/demographicterms/dg2022060126",
    "LCCNPermalink": null,
    "statusApprovedBeforeMeeting": false,
    "statusSubmittedByCoopLib": true,
    "statusNewHeading": true,
    "statusChangedHeading": false,
    "statusCancelledHeading": false,
    "statusUpdatedField": false,
    "statusAddedField": false,
    "statusDeletedField": false,
    "statusUpdatedGeog": false,
    "statusAddedGeog": false,
    "statusDeletedGeog": false,
    "statusChangedGeog": false,
    "lines": [
      "150 Forestry teachers",
      "072 occ",
      "450 UF Forest science teachers",
      "450 UF Forest sciences teachers",
      "450 UF Forestry educators",
      "450 UF Forestry instructors",
      "450 UF Forestry science teachers",
      "450 UF Forestry sciences teachers",
      "550 BT Teachers",
      "680 Teachers of forestry at any level. For teachers of students at a particular educational level, use also an occupational term for the level, e.g. University and college faculty members."
    ]
  },
  {
    "headingType": "demographicGroupTerm",
    "listDate": "2022-06-03",
    "listSource": "https://classweb.org/approved-subjects/2206x.html",
    "LCLinkedDataURI": "http://id.loc.gov/authorities/demographicterms/dg2015060588",
    "LCCNPermalink": null,
    "statusApprovedBeforeMeeting": false,
    "statusSubmittedByCoopLib": true,
    "statusNewHeading": false,
    "statusChangedHeading": false,
    "statusCancelledHeading": false,
    "statusUpdatedField": true,
    "statusAddedField": true,
    "statusDeletedField": false,
    "statusUpdatedGeog": false,
    "statusAddedGeog": false,
    "statusDeletedGeog": false,
    "statusChangedGeog": false,
    "lines": [
      "150 General practitioners (Physicians)",
      "450 UF GPs (General practitioners) ADD FIELD"
    ]
  },
  {
    "headingType": "demographicGroupTerm",
    "listDate": "2022-06-03",
    "listSource": "https://classweb.org/approved-subjects/2206x.html",
    "LCLinkedDataURI": "http://id.loc.gov/authorities/demographicterms/dg2022060133",
    "LCCNPermalink": null,
    "statusApprovedBeforeMeeting": false,
    "statusSubmittedByCoopLib": true,
    "statusNewHeading": true,
    "statusChangedHeading": false,
    "statusCancelledHeading": false,
    "statusUpdatedField": false,
    "statusAddedField": false,
    "statusDeletedField": false,
    "statusUpdatedGeog": false,
    "statusAddedGeog": false,
    "statusDeletedGeog": false,
    "statusChangedGeog": false,
    "lines": [
      "150 Gujarati speakers",
      "072 lng",
      "450 UF Gujerathi speakers",
      "450 UF Gujerati speakers",
      "450 UF Gujrathi speakers"
    ]
  },
  {
    "headingType": "demographicGroupTerm",
    "listDate": "2022-06-03",
    "listSource": "https://classweb.org/approved-subjects/2206x.html",
    "LCLinkedDataURI": "http://id.loc.gov/authorities/demographicterms/dg2022060110",
    "LCCNPermalink": null,
    "statusApprovedBeforeMeeting": false,
    "statusSubmittedByCoopLib": true,
    "statusNewHeading": true,
    "statusChangedHeading": false,
    "statusCancelledHeading": false,
    "statusUpdatedField": false,
    "statusAddedField": false,
    "statusDeletedField": false,
    "statusUpdatedGeog": false,
    "statusAddedGeog": false,
    "statusDeletedGeog": false,
    "statusChangedGeog": false,
    "lines": [
      "150 Haligonians",
      "072 nat",
      "450 UF Halifax, Nova Scotia, residents",
      "450 UF Haligoniens",
      "550 BT Nova Scotians"
    ]
  },
  {
    "headingType": "demographicGroupTerm",
    "listDate": "2022-06-03",
    "listSource": "https://classweb.org/approved-subjects/2206x.html",
    "LCLinkedDataURI": "http://id.loc.gov/authorities/demographicterms/dg2022060125",
    "LCCNPermalink": null,
    "statusApprovedBeforeMeeting": false,
    "statusSubmittedByCoopLib": true,
    "statusNewHeading": true,
    "statusChangedHeading": false,
    "statusCancelledHeading": false,
    "statusUpdatedField": false,
    "statusAddedField": false,
    "statusDeletedField": false,
    "statusUpdatedGeog": false,
    "statusAddedGeog": false,
    "statusDeletedGeog": false,
    "statusChangedGeog": false,
    "lines": [
      "150 Helsinkians",
      "072 nat",
      "450 UF Helsingforsare",
      "450 UF Helsinki, Finland, residents",
      "450 UF Helsinkiläiset",
      "550 BT Finns"
    ]
  },
  {
    "headingType": "demographicGroupTerm",
    "listDate": "2022-06-03",
    "listSource": "https://classweb.org/approved-subjects/2206x.html",
    "LCLinkedDataURI": "http://id.loc.gov/authorities/demographicterms/dg2017060020",
    "LCCNPermalink": null,
    "statusApprovedBeforeMeeting": false,
    "statusSubmittedByCoopLib": true,
    "statusNewHeading": false,
    "statusChangedHeading": false,
    "statusCancelledHeading": false,
    "statusUpdatedField": true,
    "statusAddedField": true,
    "statusDeletedField": false,
    "statusUpdatedGeog": false,
    "statusAddedGeog": false,
    "statusDeletedGeog": false,
    "statusChangedGeog": false,
    "lines": [
      "150 High school teachers",
      "681 Note under Biology teachers ADD FIELD"
    ]
  },
  {
    "headingType": "demographicGroupTerm",
    "listDate": "2022-06-03",
    "listSource": "https://classweb.org/approved-subjects/2206x.html",
    "LCLinkedDataURI": "http://id.loc.gov/authorities/demographicterms/dg2022060132",
    "LCCNPermalink": null,
    "statusApprovedBeforeMeeting": false,
    "statusSubmittedByCoopLib": true,
    "statusNewHeading": true,
    "statusChangedHeading": false,
    "statusCancelledHeading": false,
    "statusUpdatedField": false,
    "statusAddedField": false,
    "statusDeletedField": false,
    "statusUpdatedGeog": false,
    "statusAddedGeog": false,
    "statusDeletedGeog": false,
    "statusChangedGeog": false,
    "lines": [
      "150 Hindi, Students of",
      "072 soc",
      "450 UF Hindi learners",
      "450 UF Hindi students",
      "450 UF Learners, Hindi",
      "450 UF Students, Hindi",
      "450 UF Students of Hindi",
      "680 Students of Hindi language and/or Hindi literature."
    ]
  },
  {
    "headingType": "demographicGroupTerm",
    "listDate": "2022-06-03",
    "listSource": "https://classweb.org/approved-subjects/2206x.html",
    "LCLinkedDataURI": "http://id.loc.gov/authorities/demographicterms/dg2022060120",
    "LCCNPermalink": null,
    "statusApprovedBeforeMeeting": false,
    "statusSubmittedByCoopLib": true,
    "statusNewHeading": true,
    "statusChangedHeading": false,
    "statusCancelledHeading": false,
    "statusUpdatedField": false,
    "statusAddedField": false,
    "statusDeletedField": false,
    "statusUpdatedGeog": false,
    "statusAddedGeog": false,
    "statusDeletedGeog": false,
    "statusChangedGeog": false,
    "lines": [
      "150 Macedonian speakers",
      "072 lng",
      "450 UF Macedonian Slavic speakers",
      "450 UF Makedonski jazik speakers",
      "450 UF Makedonski speakers",
      "450 UF Speakers of Macedonian"
    ]
  },
  {
    "headingType": "demographicGroupTerm",
    "listDate": "2022-06-03",
    "listSource": "https://classweb.org/approved-subjects/2206x.html",
    "LCLinkedDataURI": "http://id.loc.gov/authorities/demographicterms/dg2022060119",
    "LCCNPermalink": null,
    "statusApprovedBeforeMeeting": false,
    "statusSubmittedByCoopLib": true,
    "statusNewHeading": true,
    "statusChangedHeading": false,
    "statusCancelledHeading": false,
    "statusUpdatedField": false,
    "statusAddedField": false,
    "statusDeletedField": false,
    "statusUpdatedGeog": false,
    "statusAddedGeog": false,
    "statusDeletedGeog": false,
    "statusChangedGeog": false,
    "lines": [
      "150 Macedonian, Students of",
      "072 soc",
      "450 UF Learners, Macedonian",
      "450 UF Macedonian learners",
      "450 UF Macedonian students",
      "450 UF Students, Macedonian",
      "450 UF Students of Macedonian",
      "680 Students of Macedonian language and/or Macedonian literature."
    ]
  },
  {
    "headingType": "demographicGroupTerm",
    "listDate": "2022-06-03",
    "listSource": "https://classweb.org/approved-subjects/2206x.html",
    "LCLinkedDataURI": "http://id.loc.gov/authorities/demographicterms/dg2022060098",
    "LCCNPermalink": null,
    "statusApprovedBeforeMeeting": false,
    "statusSubmittedByCoopLib": true,
    "statusNewHeading": true,
    "statusChangedHeading": false,
    "statusCancelledHeading": false,
    "statusUpdatedField": false,
    "statusAddedField": false,
    "statusDeletedField": false,
    "statusUpdatedGeog": false,
    "statusAddedGeog": false,
    "statusDeletedGeog": false,
    "statusChangedGeog": false,
    "lines": [
      "150 Miamians",
      "072 nat",
      "550 BT Floridians"
    ]
  },
  {
    "headingType": "demographicGroupTerm",
    "listDate": "2022-06-03",
    "listSource": "https://classweb.org/approved-subjects/2206x.html",
    "LCLinkedDataURI": "http://id.loc.gov/authorities/demographicterms/dg2022060123",
    "LCCNPermalink": null,
    "statusApprovedBeforeMeeting": false,
    "statusSubmittedByCoopLib": true,
    "statusNewHeading": true,
    "statusChangedHeading": false,
    "statusCancelledHeading": false,
    "statusUpdatedField": false,
    "statusAddedField": false,
    "statusDeletedField": false,
    "statusUpdatedGeog": false,
    "statusAddedGeog": false,
    "statusDeletedGeog": false,
    "statusChangedGeog": false,
    "lines": [
      "150 Minneapolitans",
      "072 nat",
      "450 UF Minneapolis, Minnesota, residents",
      "450 UF Minneapolis-Saint Paul, Minnesota, residents",
      "450 UF Minneapolis-St. Paul, Minnesota, residents",
      "450 UF Minneapolites",
      "450 UF Twin Citians (Minnesota)",
      "450 UF Twin Cities, Minnesota, residents",
      "450 UF Twin Citizens (Minnesota)",
      "550 BT Minnesotans"
    ]
  },
  {
    "headingType": "demographicGroupTerm",
    "listDate": "2022-06-03",
    "listSource": "https://classweb.org/approved-subjects/2206x.html",
    "LCLinkedDataURI": "http://id.loc.gov/authorities/demographicterms/dg2015060446",
    "LCCNPermalink": null,
    "statusApprovedBeforeMeeting": false,
    "statusSubmittedByCoopLib": true,
    "statusNewHeading": false,
    "statusChangedHeading": false,
    "statusCancelledHeading": false,
    "statusUpdatedField": true,
    "statusAddedField": true,
    "statusDeletedField": true,
    "statusUpdatedGeog": false,
    "statusAddedGeog": false,
    "statusDeletedGeog": false,
    "statusChangedGeog": false,
    "lines": [
      "150 Mormons",
      "450 UF Church of Jesus Christ of Latter-Day Saints members DELETE FIELD",
      "450 UF Latter-Day Saints DELETE FIELD",
      "450 UF Church of Jesus Christ of Latter-day Saints members ADD FIELD",
      "450 UF Latter-day Saints ADD FIELD",
      "450 UF Brighamite Mormons ADD FIELD",
      "450 UF Utah Mormons ADD FIELD",
      "450 UF Reorganized Church of Jesus Christ of Latter Day Saints members ADD FIELD",
      "450 UF Josephite Mormons ADD FIELD",
      "450 UF Reorganized Mormons ADD FIELD",
      "450 UF RLDS Mormons ADD FIELD",
      "450 UF Church of Jesus Christ (Strangites) members ADD FIELD",
      "450 UF Strangite Mormons ADD FIELD",
      "450 UF Church of Christ (Temple Lot) members ADD FIELD",
      "450 UF Hedrikites ADD FIELD",
      "450 UF Temple Lot Mormons ADD FIELD"
    ]
  },
  {
    "headingType": "demographicGroupTerm",
    "listDate": "2022-06-03",
    "listSource": "https://classweb.org/approved-subjects/2206x.html",
    "LCLinkedDataURI": "http://id.loc.gov/authorities/demographicterms/dg2022060115",
    "LCCNPermalink": null,
    "statusApprovedBeforeMeeting": false,
    "statusSubmittedByCoopLib": true,
    "statusNewHeading": true,
    "statusChangedHeading": false,
    "statusCancelledHeading": false,
    "statusUpdatedField": false,
    "statusAddedField": false,
    "statusDeletedField": false,
    "statusUpdatedGeog": false,
    "statusAddedGeog": false,
    "statusDeletedGeog": false,
    "statusChangedGeog": false,
    "lines": [
      "150 Norwegian, Students of",
      "072 soc",
      "450 UF Learners, Norwegian",
      "450 UF Norwegian learners",
      "450 UF Norwegian students",
      "450 UF Students, Norwegian",
      "450 UF Students of Norwegian",
      "680 Students of Norwegian language and/or Norwegian literature."
    ]
  },
  {
    "headingType": "demographicGroupTerm",
    "listDate": "2022-06-03",
    "listSource": "https://classweb.org/approved-subjects/2206x.html",
    "LCLinkedDataURI": "http://id.loc.gov/authorities/demographicterms/dg2022060131",
    "LCCNPermalink": null,
    "statusApprovedBeforeMeeting": false,
    "statusSubmittedByCoopLib": true,
    "statusNewHeading": true,
    "statusChangedHeading": false,
    "statusCancelledHeading": false,
    "statusUpdatedField": false,
    "statusAddedField": false,
    "statusDeletedField": false,
    "statusUpdatedGeog": false,
    "statusAddedGeog": false,
    "statusDeletedGeog": false,
    "statusChangedGeog": false,
    "lines": [
      "150 Policy scientists",
      "072 occ",
      "450 UF Scientists, Policy",
      "550 RT Political scientists"
    ]
  },
  {
    "headingType": "demographicGroupTerm",
    "listDate": "2022-06-03",
    "listSource": "https://classweb.org/approved-subjects/2206x.html",
    "LCLinkedDataURI": "http://id.loc.gov/authorities/demographicterms/dg2022060101",
    "LCCNPermalink": null,
    "statusApprovedBeforeMeeting": false,
    "statusSubmittedByCoopLib": true,
    "statusNewHeading": true,
    "statusChangedHeading": false,
    "statusCancelledHeading": false,
    "statusUpdatedField": false,
    "statusAddedField": false,
    "statusDeletedField": false,
    "statusUpdatedGeog": false,
    "statusAddedGeog": false,
    "statusDeletedGeog": false,
    "statusChangedGeog": false,
    "lines": [
      "150 Polish, Students of",
      "072 soc",
      "450 UF Learners, Polish",
      "450 UF Polish learners",
      "450 UF Polish students",
      "450 UF Students, Polish",
      "450 UF Students of Polish",
      "680 Students of Polish language and/or Polish literature."
    ]
  },
  {
    "headingType": "demographicGroupTerm",
    "listDate": "2022-06-03",
    "listSource": "https://classweb.org/approved-subjects/2206x.html",
    "LCLinkedDataURI": "http://id.loc.gov/authorities/demographicterms/dg2015060597",
    "LCCNPermalink": null,
    "statusApprovedBeforeMeeting": false,
    "statusSubmittedByCoopLib": true,
    "statusNewHeading": false,
    "statusChangedHeading": false,
    "statusCancelledHeading": false,
    "statusUpdatedField": true,
    "statusAddedField": true,
    "statusDeletedField": false,
    "statusUpdatedGeog": false,
    "statusAddedGeog": false,
    "statusDeletedGeog": false,
    "statusChangedGeog": false,
    "lines": [
      "150 Political scientists",
      "550 RT Policy scientists ADD FIELD"
    ]
  },
  {
    "headingType": "demographicGroupTerm",
    "listDate": "2022-06-03",
    "listSource": "https://classweb.org/approved-subjects/2206x.html",
    "LCLinkedDataURI": "http://id.loc.gov/authorities/demographicterms/dg2022060109",
    "LCCNPermalink": null,
    "statusApprovedBeforeMeeting": false,
    "statusSubmittedByCoopLib": true,
    "statusNewHeading": true,
    "statusChangedHeading": false,
    "statusCancelledHeading": false,
    "statusUpdatedField": false,
    "statusAddedField": false,
    "statusDeletedField": false,
    "statusUpdatedGeog": false,
    "statusAddedGeog": false,
    "statusDeletedGeog": false,
    "statusChangedGeog": false,
    "lines": [
      "150 Portuguese, Students of",
      "072 soc",
      "450 UF Learners, Portuguese",
      "450 UF Portuguese learners",
      "450 UF Portuguese students",
      "450 UF Students, Portuguese",
      "450 UF Students of Portuguese",
      "680 Students of Portuguese language and/or Portuguese literature."
    ]
  },
  {
    "headingType": "demographicGroupTerm",
    "listDate": "2022-06-03",
    "listSource": "https://classweb.org/approved-subjects/2206x.html",
    "LCLinkedDataURI": "http://id.loc.gov/authorities/demographicterms/dg2022060112",
    "LCCNPermalink": null,
    "statusApprovedBeforeMeeting": false,
    "statusSubmittedByCoopLib": true,
    "statusNewHeading": true,
    "statusChangedHeading": false,
    "statusCancelledHeading": false,
    "statusUpdatedField": false,
    "statusAddedField": false,
    "statusDeletedField": false,
    "statusUpdatedGeog": false,
    "statusAddedGeog": false,
    "statusDeletedGeog": false,
    "statusChangedGeog": false,
    "lines": [
      "150 Praguers",
      "072 nat",
      "450 UF Pražané",
      "550 BT Czechs"
    ]
  },
  {
    "headingType": "demographicGroupTerm",
    "listDate": "2022-06-03",
    "listSource": "https://classweb.org/approved-subjects/2206x.html",
    "LCLinkedDataURI": "http://id.loc.gov/authorities/demographicterms/dg2015060166",
    "LCCNPermalink": null,
    "statusApprovedBeforeMeeting": false,
    "statusSubmittedByCoopLib": true,
    "statusNewHeading": false,
    "statusChangedHeading": false,
    "statusCancelledHeading": false,
    "statusUpdatedField": true,
    "statusAddedField": true,
    "statusDeletedField": false,
    "statusUpdatedGeog": false,
    "statusAddedGeog": false,
    "statusDeletedGeog": false,
    "statusChangedGeog": false,
    "lines": [
      "150 Puerto Ricans",
      "450 UF Boricuas ADD FIELD"
    ]
  },
  {
    "headingType": "demographicGroupTerm",
    "listDate": "2022-06-03",
    "listSource": "https://classweb.org/approved-subjects/2206x.html",
    "LCLinkedDataURI": "http://id.loc.gov/authorities/demographicterms/dg2015060189",
    "LCCNPermalink": null,
    "statusApprovedBeforeMeeting": false,
    "statusSubmittedByCoopLib": true,
    "statusNewHeading": false,
    "statusChangedHeading": true,
    "statusCancelledHeading": false,
    "statusUpdatedField": false,
    "statusAddedField": false,
    "statusDeletedField": false,
    "statusUpdatedGeog": false,
    "statusAddedGeog": false,
    "statusDeletedGeog": false,
    "statusChangedGeog": false,
    "lines": [
      "150 Quebeckers CHANGE HEADING",
      "150 Quebeckers (Province of Québec)",
      "072 nat",
      "450 UF Québec residents",
      "450 UF Quebecers (Province of Québec)",
      "450 UF Quebeckers [Former heading]",
      "450 UF Québécois (Province of Québec)",
      "450 UF Québécois du Québec",
      "550 BT Canadians"
    ]
  },
  {
    "headingType": "demographicGroupTerm",
    "listDate": "2022-06-03",
    "listSource": "https://classweb.org/approved-subjects/2206x.html",
    "LCLinkedDataURI": "http://id.loc.gov/authorities/demographicterms/dg2022060111",
    "LCCNPermalink": null,
    "statusApprovedBeforeMeeting": false,
    "statusSubmittedByCoopLib": true,
    "statusNewHeading": true,
    "statusChangedHeading": false,
    "statusCancelledHeading": false,
    "statusUpdatedField": false,
    "statusAddedField": false,
    "statusDeletedField": false,
    "statusUpdatedGeog": false,
    "statusAddedGeog": false,
    "statusDeletedGeog": false,
    "statusChangedGeog": false,
    "lines": [
      "150 Québécois (Québec City)",
      "072 nat",
      "450 UF Capitaliens (Québec City)",
      "450 UF Québec, Québec, residents",
      "450 UF Québec City, Québec, residents",
      "450 UF Quebecers (Québec City)",
      "450 UF Quebeckers (Québec City)",
      "450 UF Québécois de Québec",
      "550 BT Quebeckers (Province of Québec)"
    ]
  },
  {
    "headingType": "demographicGroupTerm",
    "listDate": "2022-06-03",
    "listSource": "https://classweb.org/approved-subjects/2206x.html",
    "LCLinkedDataURI": "http://id.loc.gov/authorities/demographicterms/dg2022060124",
    "LCCNPermalink": null,
    "statusApprovedBeforeMeeting": false,
    "statusSubmittedByCoopLib": true,
    "statusNewHeading": true,
    "statusChangedHeading": false,
    "statusCancelledHeading": false,
    "statusUpdatedField": false,
    "statusAddedField": false,
    "statusDeletedField": false,
    "statusUpdatedGeog": false,
    "statusAddedGeog": false,
    "statusDeletedGeog": false,
    "statusChangedGeog": false,
    "lines": [
      "150 Saint Paulites",
      "072 nat",
      "450 UF Minneapolis-Saint Paul, Minnesota, residents",
      "450 UF Minneapolis-St. Paul, Minnesota, residents",
      "450 UF Saint Paul, Minnesota, residents",
      "450 UF Saint Paulians",
      "450 UF St. Paul, Minnesota, residents",
      "450 UF St. Paulians",
      "450 UF St. Paulites",
      "450 UF Twin Citians (Minnesota)",
      "450 UF Twin Cities, Minnesota, residents",
      "450 UF Twin Citizens (Minnesota)",
      "550 BT Minnesotans"
    ]
  },
  {
    "headingType": "demographicGroupTerm",
    "listDate": "2022-06-03",
    "listSource": "https://classweb.org/approved-subjects/2206x.html",
    "LCLinkedDataURI": "http://id.loc.gov/authorities/demographicterms/dg2015060809",
    "LCCNPermalink": null,
    "statusApprovedBeforeMeeting": false,
    "statusSubmittedByCoopLib": true,
    "statusNewHeading": false,
    "statusChangedHeading": false,
    "statusCancelledHeading": false,
    "statusUpdatedField": true,
    "statusAddedField": true,
    "statusDeletedField": true,
    "statusUpdatedGeog": false,
    "statusAddedGeog": false,
    "statusDeletedGeog": false,
    "statusChangedGeog": false,
    "lines": [
      "150 Slovak speakers",
      "450 UF Slovencina speakers DELETE FIELD",
      "450 UF Slovenčina speakers ADD FIELD",
      "450 UF Slovenský jazyk speakers ADD FIELD",
      "450 UF Speakers of Slovak ADD FIELD"
    ]
  },
  {
    "headingType": "demographicGroupTerm",
    "listDate": "2022-06-03",
    "listSource": "https://classweb.org/approved-subjects/2206x.html",
    "LCLinkedDataURI": "http://id.loc.gov/authorities/demographicterms/dg2015060499",
    "LCCNPermalink": null,
    "statusApprovedBeforeMeeting": false,
    "statusSubmittedByCoopLib": true,
    "statusNewHeading": false,
    "statusChangedHeading": false,
    "statusCancelledHeading": false,
    "statusUpdatedField": true,
    "statusAddedField": true,
    "statusDeletedField": true,
    "statusUpdatedGeog": false,
    "statusAddedGeog": false,
    "statusDeletedGeog": false,
    "statusChangedGeog": false,
    "lines": [
      "150 Slovene speakers",
      "450 UF Slovenscina speakers DELETE FIELD",
      "450 UF Slovenščina speakers ADD FIELD",
      "450 UF Speakers of Slovene ADD FIELD",
      "450 UF Speakers of Slovenian ADD FIELD"
    ]
  },
  {
    "headingType": "demographicGroupTerm",
    "listDate": "2022-06-03",
    "listSource": "https://classweb.org/approved-subjects/2206x.html",
    "LCLinkedDataURI": "http://id.loc.gov/authorities/demographicterms/dg2022060117",
    "LCCNPermalink": null,
    "statusApprovedBeforeMeeting": false,
    "statusSubmittedByCoopLib": true,
    "statusNewHeading": true,
    "statusChangedHeading": false,
    "statusCancelledHeading": false,
    "statusUpdatedField": false,
    "statusAddedField": false,
    "statusDeletedField": false,
    "statusUpdatedGeog": false,
    "statusAddedGeog": false,
    "statusDeletedGeog": false,
    "statusChangedGeog": false,
    "lines": [
      "150 Slovene, Students of",
      "072 soc",
      "450 UF Learners, Slovene",
      "450 UF Learners, Slovenian",
      "450 UF Slovene learners",
      "450 UF Slovene students",
      "450 UF Slovenian, Students of",
      "450 UF Slovenian learners",
      "450 UF Slovenian students",
      "450 UF Students, Slovene",
      "450 UF Students, Slovenian",
      "450 UF Students of Slovene",
      "450 UF Students of Slovenian",
      "680 Students of Slovene language and/or Slovene literature."
    ]
  },
  {
    "headingType": "demographicGroupTerm",
    "listDate": "2022-06-03",
    "listSource": "https://classweb.org/approved-subjects/2206x.html",
    "LCLinkedDataURI": "http://id.loc.gov/authorities/demographicterms/dg2022060122",
    "LCCNPermalink": null,
    "statusApprovedBeforeMeeting": false,
    "statusSubmittedByCoopLib": true,
    "statusNewHeading": true,
    "statusChangedHeading": false,
    "statusCancelledHeading": false,
    "statusUpdatedField": false,
    "statusAddedField": false,
    "statusDeletedField": false,
    "statusUpdatedGeog": false,
    "statusAddedGeog": false,
    "statusDeletedGeog": false,
    "statusChangedGeog": false,
    "lines": [
      "150 Staten Islanders",
      "072 nat",
      "450 UF Richmond, New York, residents",
      "450 UF Richmond County, New York, residents",
      "450 UF Staten Island, New York, residents",
      "550 BT New Yorkers (New York City)"
    ]
  },
  {
    "headingType": "demographicGroupTerm",
    "listDate": "2022-06-03",
    "listSource": "https://classweb.org/approved-subjects/2206x.html",
    "LCLinkedDataURI": "http://id.loc.gov/authorities/demographicterms/dg2022060129",
    "LCCNPermalink": null,
    "statusApprovedBeforeMeeting": false,
    "statusSubmittedByCoopLib": true,
    "statusNewHeading": true,
    "statusChangedHeading": false,
    "statusCancelledHeading": false,
    "statusUpdatedField": false,
    "statusAddedField": false,
    "statusDeletedField": false,
    "statusUpdatedGeog": false,
    "statusAddedGeog": false,
    "statusDeletedGeog": false,
    "statusChangedGeog": false,
    "lines": [
      "150 Tajik speakers",
      "072 lng",
      "450 UF Forsii tojikī speakers",
      "450 UF Persian, Tajiki, speakers",
      "450 UF Tadjik speakers",
      "450 UF Tadzhik speakers",
      "450 UF Tadzhiki speakers",
      "450 UF Tajiki speakers",
      "450 UF Tajiki Persian speakers",
      "450 UF Tojikī speakers"
    ]
  },
  {
    "headingType": "demographicGroupTerm",
    "listDate": "2022-06-03",
    "listSource": "https://classweb.org/approved-subjects/2206x.html",
    "LCLinkedDataURI": "http://id.loc.gov/authorities/demographicterms/dg2022060099",
    "LCCNPermalink": null,
    "statusApprovedBeforeMeeting": false,
    "statusSubmittedByCoopLib": true,
    "statusNewHeading": true,
    "statusChangedHeading": false,
    "statusCancelledHeading": false,
    "statusUpdatedField": false,
    "statusAddedField": false,
    "statusDeletedField": false,
    "statusUpdatedGeog": false,
    "statusAddedGeog": false,
    "statusDeletedGeog": false,
    "statusChangedGeog": false,
    "lines": [
      "150 Tamil, Students of",
      "072 soc",
      "450 UF Learners, Tamil",
      "450 UF Students, Tamil",
      "450 UF Students of Tamil",
      "450 UF Tamil learners",
      "450 UF Tamil students",
      "680 Students of Tamil language and/or Tamil literature."
    ]
  },
  {
    "headingType": "demographicGroupTerm",
    "listDate": "2022-06-03",
    "listSource": "https://classweb.org/approved-subjects/2206x.html",
    "LCLinkedDataURI": "http://id.loc.gov/authorities/demographicterms/dg2022060102",
    "LCCNPermalink": null,
    "statusApprovedBeforeMeeting": false,
    "statusSubmittedByCoopLib": true,
    "statusNewHeading": true,
    "statusChangedHeading": false,
    "statusCancelledHeading": false,
    "statusUpdatedField": false,
    "statusAddedField": false,
    "statusDeletedField": false,
    "statusUpdatedGeog": false,
    "statusAddedGeog": false,
    "statusDeletedGeog": false,
    "statusChangedGeog": false,
    "lines": [
      "150 Tel Avivians",
      "072 nat",
      "450 UF Tel Avivans",
      "450 UF Tel Avivi",
      "550 BT Israelis"
    ]
  },
  {
    "headingType": "demographicGroupTerm",
    "listDate": "2022-06-03",
    "listSource": "https://classweb.org/approved-subjects/2206x.html",
    "LCLinkedDataURI": "http://id.loc.gov/authorities/demographicterms/dg2016060024",
    "LCCNPermalink": null,
    "statusApprovedBeforeMeeting": false,
    "statusSubmittedByCoopLib": true,
    "statusNewHeading": false,
    "statusChangedHeading": false,
    "statusCancelledHeading": false,
    "statusUpdatedField": true,
    "statusAddedField": true,
    "statusDeletedField": false,
    "statusUpdatedGeog": false,
    "statusAddedGeog": false,
    "statusDeletedGeog": false,
    "statusChangedGeog": false,
    "lines": [
      "150 University and college faculty members",
      "450 UF College faculty members ADD FIELD",
      "450 UF University faculty members ADD FIELD",
      "550 BT Teachers ADD FIELD",
      "681 Note under Forestry teachers ADD FIELD"
    ]
  },
  {
    "headingType": "demographicGroupTerm",
    "listDate": "2022-06-03",
    "listSource": "https://classweb.org/approved-subjects/2206x.html",
    "LCLinkedDataURI": "http://id.loc.gov/authorities/demographicterms/dg2022060024",
    "LCCNPermalink": null,
    "statusApprovedBeforeMeeting": false,
    "statusSubmittedByCoopLib": true,
    "statusNewHeading": false,
    "statusChangedHeading": false,
    "statusCancelledHeading": false,
    "statusUpdatedField": true,
    "statusAddedField": true,
    "statusDeletedField": false,
    "statusUpdatedGeog": false,
    "statusAddedGeog": false,
    "statusDeletedGeog": false,
    "statusChangedGeog": false,
    "lines": [
      "150 Vancouverites (British Columbia)",
      "450 UF Vancouveriens (British Columbia) ADD FIELD",
      "450 UF Vancouvérois (British Columbia) ADD FIELD"
    ]
  },
  {
    "headingType": "demographicGroupTerm",
    "listDate": "2022-06-03",
    "listSource": "https://classweb.org/approved-subjects/2206x.html",
    "LCLinkedDataURI": "http://id.loc.gov/authorities/demographicterms/dg2016060498",
    "LCCNPermalink": null,
    "statusApprovedBeforeMeeting": false,
    "statusSubmittedByCoopLib": true,
    "statusNewHeading": true,
    "statusChangedHeading": false,
    "statusCancelledHeading": false,
    "statusUpdatedField": false,
    "statusAddedField": false,
    "statusDeletedField": false,
    "statusUpdatedGeog": false,
    "statusAddedGeog": false,
    "statusDeletedGeog": false,
    "statusChangedGeog": false,
    "lines": [
      "150 Video gamers",
      "072 occ",
      "450 UF Computer game players",
      "450 UF Computer gamers",
      "450 UF Electronic game players",
      "450 UF Electronic gamers",
      "450 UF Game players, Computer",
      "450 UF Game players, Electronic",
      "450 UF Game players, Role-playing video",
      "450 UF Game players, Video",
      "450 UF Gamers, Computer",
      "450 UF Gamers, Electronic",
      "450 UF Gamers, Role-playing video",
      "450 UF Gamers, Video",
      "450 UF Role players (Video gamers)",
      "450 UF Role-playing video game players",
      "450 UF RPG players, Video",
      "450 UF Video game players",
      "450 UF Video role-playing game players",
      "450 UF Video RPG players",
      "680 Players of electronic, computer, and video games."
    ]
  },
  {
    "headingType": "demographicGroupTerm",
    "listDate": "2022-06-03",
    "listSource": "https://classweb.org/approved-subjects/2206x.html",
    "LCLinkedDataURI": "http://id.loc.gov/authorities/demographicterms/dg2016060378",
    "LCCNPermalink": null,
    "statusApprovedBeforeMeeting": false,
    "statusSubmittedByCoopLib": true,
    "statusNewHeading": false,
    "statusChangedHeading": false,
    "statusCancelledHeading": false,
    "statusUpdatedField": true,
    "statusAddedField": true,
    "statusDeletedField": true,
    "statusUpdatedGeog": false,
    "statusAddedGeog": false,
    "statusDeletedGeog": false,
    "statusChangedGeog": false,
    "lines": [
      "150 White people",
      "450 UF Caucasians (Whites) DELETE FIELD",
      "450 UF Caucasians (White people) ADD FIELD"
    ]
  },
  {
    "headingType": "demographicGroupTerm",
    "listDate": "2022-06-03",
    "listSource": "https://classweb.org/approved-subjects/2206x.html",
    "LCLinkedDataURI": "http://id.loc.gov/authorities/demographicterms/dg2022060114",
    "LCCNPermalink": null,
    "statusApprovedBeforeMeeting": false,
    "statusSubmittedByCoopLib": true,
    "statusNewHeading": true,
    "statusChangedHeading": false,
    "statusCancelledHeading": false,
    "statusUpdatedField": false,
    "statusAddedField": false,
    "statusDeletedField": false,
    "statusUpdatedGeog": false,
    "statusAddedGeog": false,
    "statusDeletedGeog": false,
    "statusChangedGeog": false,
    "lines": [
      "150 Zurichers (Canton of Zurich)",
      "072 nat",
      "450 UF Zürcher (Canton of Zurich)",
      "450 UF Zurichois (Canton of Zurich)",
      "550 BT Swiss"
    ]
  }
]
